codemood/__init__.py
codemood/advanced_analyzer.py
codemood/code_mood_analyzer.py
codemood/model_loader.py
codemood/optimization_engine.py
codemood/performance_analyzer.py
codemood/security_analyzer.py
codemood/sentiment_engine.py
codemood/unified_analyzer.py
codemood/_stubs/huggingface_hub.pyi
codemood/_stubs/transformers.pyi
codemood-0.2.0.dist-info/licenses/LICENSE
examples/advanced_sentiment_demo.py
examples/advanced_usage.py
examples/ai_enhanced_demo.py
model_training/dataset_collector.py
model_training/model_trainer.py
tests/test_advanced.py
tests/test_basic.py
tests/test_sentiment_optimization.py
codemood-0.2.0.dist-info/METADATA
codemood-0.2.0.dist-info/WHEEL
codemood-0.2.0.dist-info/top_level.txt
codemood-0.2.0.dist-info/RECORD
