Metadata-Version: 2.4
Name: codemood
Version: 0.2.0
Summary: Advanced Code Mood Analyzer with sentiment analysis, optimization suggestions, custom model training, and comprehensive code quality assessment
Home-page: https://github.com/OmkarPalika/codemood
Author: Omkar Palika
Author-email: Omkar Palika <palikaomkar.22.cse@anits.edu.in>
License: MIT License
Project-URL: Homepage, https://github.com/OmkarPalika/codemood
Project-URL: Issues, https://github.com/OmkarPalika/codemood/issues
Keywords: code,sentiment,analysis,optimization,AI,machine-learning,code-quality,security,performance
Classifier: Development Status :: 3 - Alpha
Classifier: Intended Audience :: Developers
Classifier: License :: OSI Approved :: MIT License
Classifier: Programming Language :: Python :: 3.8
Classifier: Programming Language :: Python :: 3.9
Classifier: Programming Language :: Python :: 3.10
Classifier: Programming Language :: Python :: 3.11
Requires-Python: >=3.8
License-File: LICENSE
Requires-Dist: transformers>=4.40.0
Requires-Dist: huggingface_hub>=0.23.0
Requires-Dist: matplotlib
Requires-Dist: torch>=1.9.0
Provides-Extra: dev
Requires-Dist: pytest>=6.0; extra == "dev"
Requires-Dist: flake8>=4.0.0; extra == "dev"
Requires-Dist: black>=22.0.0; extra == "dev"
Requires-Dist: mypy>=0.950; extra == "dev"
Dynamic: license-file
